indico_sso_group_mapping/__init__.py
indico_sso_group_mapping/plugin.py
indico_sso_group_mapping/task.py
indico_sso_group_mapping-1.0.2.dist-info/METADATA
indico_sso_group_mapping-1.0.2.dist-info/WHEEL
indico_sso_group_mapping-1.0.2.dist-info/entry_points.txt
indico_sso_group_mapping-1.0.2.dist-info/licenses/LICENSE
indico_sso_group_mapping-1.0.2.dist-info/RECORD
