Metadata-Version: 2.3
Name: indico-sso-group-mapping
Version: 1.0.2
Summary: SSO group mapping plugin for Indico
Project-URL: GitHub, https://github.com/unibonn/indico-sso-group-mapping
Author: University of Bonn
License-Expression: MIT
License-File: LICENSE
Classifier: Environment :: Plugins
Classifier: Environment :: Web Environment
Classifier: License :: OSI Approved :: MIT License
Classifier: Programming Language :: Python :: 3.12
Requires-Python: <3.13,>=3.12.2
Requires-Dist: indico>=3.3
